LICENSE
MANIFEST.in
README.rst
relopy
setup.py
Relo.egg-info/SOURCES.txt
relo/.DS_Store
relo/__init__.py
relo.egg-info/PKG-INFO
relo.egg-info/SOURCES.txt
relo.egg-info/dependency_links.txt
relo.egg-info/requires.txt
relo.egg-info/top_level.txt
relo/core/.DS_Store
relo/core/__init__.py
relo/core/config.py
relo/core/exceptions.py
relo/core/interfaces.py
relo/core/log.py
relo/core/update.py
relo/core/util.py
relo/core/backend/.DS_Store
relo/core/backend/__init__.py
relo/core/backend/redisdb.py
relo/core/backend/redisdb.relo
relo/core/doctype/__init__.py
relo/core/doctype/default.py
relo/core/doctype/default.relo
relo/core/doctype/log.py
relo/core/doctype/log.relo
relo/core/doctype/pdf.py
relo/core/doctype/pdf.relo
relo/core/doctype/test.py
relo/core/doctype/test.relo
relo/core/doctype/txt.py
relo/core/doctype/txt.relo
relo/core/etc/config.cfg
relo/local/__init__.py
relo/local/extract.py
relo/local/index.py
relo/local/metaphone.py
relo/local/search.py
relo/local/stats.py
relo/local/util.py
relo/local/statistics/__init__.py
relo/local/statistics/disk-space copy.py
relo/local/statistics/disk-space.py
relo/local/statistics/diskspace.py
relo/local/statistics/diskspace.relo
relo/net/__init__.py
relo/net/crawl.py
relo/net/download.py
relo/yapsy/AutoInstallPluginManager.py
relo/yapsy/ConfigurablePluginManager.py
relo/yapsy/FilteredPluginManager.py
relo/yapsy/IPlugin.py
relo/yapsy/PluginInfo.py
relo/yapsy/PluginManager.py
relo/yapsy/PluginManagerDecorator.py
relo/yapsy/VersionedPluginManager.py
relo/yapsy/__init__.py